LICENSE
MANIFEST.in
README.rst
setup.py
django_generic_feeds.egg-info/PKG-INFO
django_generic_feeds.egg-info/SOURCES.txt
django_generic_feeds.egg-info/dependency_links.txt
django_generic_feeds.egg-info/requires.txt
django_generic_feeds.egg-info/top_level.txt
feeds/__init__.py
feeds/models.py
feeds/tests.py