Metadata-Version: 1.1
Name: django-generic-feeds
Version: 0.1.5
Summary: 
